textual_window/__init__.py
textual_window/button_bases.py
textual_window/demo.py
textual_window/demostyles.tcss
textual_window/manager.py
textual_window/py.typed
textual_window/switcher.py
textual_window/window.py
textual_window/windowbar.py
textual_window/windowcomponents.py
textual_window-0.8.1.dist-info/METADATA
textual_window-0.8.1.dist-info/WHEEL
textual_window-0.8.1.dist-info/entry_points.txt
textual_window-0.8.1.dist-info/RECORD
