Metadata-Version: 2.4
Name: textual-window
Version: 0.8.1
Summary: A Textual widget for a floating, draggable window and included window bar/manager system.
Project-URL: Repository, https://github.com/edward-jazzhands/textual-window
Project-URL: Changelog, https://github.com/edward-jazzhands/textual-window/blob/master/CHANGELOG.md
Author-email: edward-jazzhands <ed.jazzhands@gmail.com>
License: MIT
Keywords: python,textual,tui,widget,window
Classifier: Development Status :: 4 - Beta
Classifier: License :: OSI Approved :: MIT License
Classifier: Operating System :: OS Independent
Classifier: Programming Language :: Python
Classifier: Programming Language :: Python :: 3 :: Only
Classifier: Programming Language :: Python :: 3.9
Classifier: Programming Language :: Python :: 3.10
Classifier: Programming Language :: Python :: 3.11
Classifier: Programming Language :: Python :: 3.12
Classifier: Programming Language :: Python :: 3.13
Requires-Python: >=3.9
Requires-Dist: ezpubsub>=0.3.0
Requires-Dist: textual<6.0.0,>=5.1.0
